weather_query/__init__.py
weather_query/core.py
weather_query/test_query.py
weather_query-0.1.3.dist-info/METADATA
weather_query-0.1.3.dist-info/WHEEL
weather_query-0.1.3.dist-info/top_level.txt
weather_query-0.1.3.dist-info/RECORD
