Metadata-Version: 2.1
Name: weather_query
Version: 0.1.3
Summary: My sample package
Home-page: https://github.com/minsung8/weather_project
Author: minsung8
Author-email: alstjddl8@naver.com
Classifier: Programming Language :: Python :: 3
Classifier: License :: OSI Approved :: MIT License
Classifier: Operating System :: OS Independent
Requires-Python: >=3.9
